jptranscription/__init__.py
jptranscription/phonetics/__init__.py
jptranscription/phonetics/phonetizer.py
jptranscription/phonetics/wikitionary_processor.py
jptranscription/transcription/__init__.py
jptranscription/transcription/ipakatamapping.py
jptranscription/transcription/katakanizer.py
jptranscription-0.1.6.dist-info/LICENSE
jptranscription-0.1.6.dist-info/METADATA
jptranscription-0.1.6.dist-info/WHEEL
jptranscription-0.1.6.dist-info/top_level.txt
jptranscription-0.1.6.dist-info/RECORD
